README.md
setup.py
lzkyyds/__init__.py
lzkyyds/ad.py
lzkyyds/yyds.py
lzkyyds.egg-info/PKG-INFO
lzkyyds.egg-info/SOURCES.txt
lzkyyds.egg-info/dependency_links.txt
lzkyyds.egg-info/requires.txt
lzkyyds.egg-info/top_level.txt