Metadata-Version: 2.1
Name: lzkyyds
Version: 0.1.5
Summary: android python script engine
Home-page: https://github.com/liuzika
Author: lzk
Author-email: lzkiiau@outlook.com
License: UNKNOWN
Platform: UNKNOWN
Classifier: Programming Language :: Python :: 3
Classifier: License :: OSI Approved :: MIT License
Classifier: Operating System :: OS Independent
